pycord_reactive_views/__init__.py
pycord_reactive_views/_version.py
pycord_reactive_views/components.py
pycord_reactive_views/view.py
pycord_reactive_views/utils/__init__.py
pycord_reactive_views/utils/reactivity.py
pycord_reactive_views-1.0.3.dist-info/METADATA
pycord_reactive_views-1.0.3.dist-info/WHEEL
pycord_reactive_views-1.0.3.dist-info/licenses/LICENSE
pycord_reactive_views-1.0.3.dist-info/RECORD
