Metadata-Version: 2.4
Name: pycord-reactive-views
Version: 1.0.3
Summary: A py-cord extension for easy creation of reactive views
Project-URL: Homepage, https://github.com/Paillat-dev/pycord-reactive-views
Project-URL: source_archive, https://github.com/Paillat-dev/pycord-reactive-views/archive/87c7211ab1e25b3a815819f18cb058ee142d9d2c.zip
Author-email: Paillat-dev <me@paillat.dev>
License: MIT
License-File: LICENSE
Classifier: Development Status :: 3 - Alpha
Classifier: Intended Audience :: Developers
Classifier: License :: OSI Approved :: MIT License
Classifier: Programming Language :: Python :: 3 :: Only
Classifier: Programming Language :: Python :: 3.11
Classifier: Programming Language :: Python :: 3.12
Requires-Python: >=3.11
Requires-Dist: py-cord>=2.6.0
Requires-Dist: typing-extensions<5,>=4.4.0
